{
  "events": [
    {
      "id": 1,
      "title": "Антонио Вивальди. Времена года",
      "mainImg": "img/c499835e11691b8d4176b47885dfc6e6.jpg",
      "info": [
        {
          "heading": "Санкт-Петербургский камерный оркестр Olympic Orchestra",
          "content": "Солистка – Надежда Троицкая (скрипка)\nДирижёр – Илья Филькенштейн\nХудожественный руководитель - Алексей Степанов"
        },
        {
          "heading": "",
          "content": "Музыка Вивальди на века!!! Изысканная роскошь, пышность и причудливая эстетика эпохи барокко в полной мере нашли воплощение в творчестве знаменитого венецианца Антонио Вивальди. Его называют «итальянским Бахом», и неспроста: за 63 года жизни музыкант написал около 800 произведений, включая оперы, хоровые произведения, более 500 концертов для различных инструментов и оркестра. Талантливый композитор-новатор, виртуозный скрипач, блестящий дирижер и педагог, он оставил после себя богатейшее творческое наследие.\nВ первом отделении прозвучит знаменитый цикл «Времена года» Антонио Вивальди, второе же отделение будет посвящено мелодичным серенадам для струнного оркестра Эдуарда Элгара и Петра Ильича Чайковского."
        },
        {
          "heading": "Программа концерта",
          "content": "1 отделение\nА. Вивальди «Времена года»:\nКонцерт № 1 ми мажор «Весна»\nКонцерт № 2 соль минор «Лето»\nКонцерт № 3 фа мажор «Осень»\nКонцерт № 4 фа минор «Зима»\n2 отделение\nЭ. Элгар «Серенада для струнного оркестра»\nП. Чайковский «Серенада для струнного оркестра»"
        }
      ],
      "price": "700-1900 руб.",
      "ticketlink": "#",
      "secondaryImg": [
        "img/c499835e11691b8d4176b47885dfc6e6.jpg",
        "img/c499835e11691b8d4176b47885dfc6e6.jpg"
      ]
    }
  ],
  "month": "2024-07",
  "modes": [
    {
      "title": "Обзорные экскурсии",
      "image": "img/cd73a34cf83ca6bbeb91f5a39f002d09.jpg",
      "events": {
        "2024-07-02": "#",
        "2024-07-05": "#",
        "2024-07-07": "#",
        "2024-07-09": "#",
        "2024-07-12": "#",
        "2024-07-14": "#",
        "2024-07-16": "#",
        "2024-07-19": "#",
        "2024-07-21": "#",
        "2024-07-23": "#",
        "2024-07-26": "#",
        "2024-07-28": "#",
        "2024-07-30": "#"
      }
    },
    {
      "title": "Концерты",
      "image": "img/03a43cdcea0377b70240ae14f0211a87.jpg",
      "events": {
        "2024-07-03": "#",
        "2024-07-06": "#",
        "2024-07-10": "#",
        "2024-07-13": "#",
        "2024-07-17": "#",
        "2024-07-20": "#",
        "2024-07-24": "#",
        "2024-07-27": "#"
      }
    }
  ]
}